<annotation>
  <folder>input</folder>
  <filename>ramayana-28.png</filename>
  <path>C:\Users\defaultuser0\Desktop\OpenLabeling-master\main\input\ramayana-28.png</path>
  <source>
    <database>Unknown</database>
  </source>
  <size>
    <width>1142</width>
    <height>1654</height>
    <depth>3</depth>
  </size>
  <segmented>0</segmented>
  <object>
    <name>thai</name>
    <pose>Unspecified</pose>
    <truncated>0</truncated>
    <difficult>0</difficult>
    <bndbox>
      <xmin>630</xmin>
      <ymin>33</ymin>
      <xmax>937</xmax>
      <ymax>77</ymax>
    </bndbox>
  </object>
  <object>
    <name>thai</name>
    <pose>Unspecified</pose>
    <truncated>0</truncated>
    <difficult>0</difficult>
    <bndbox>
      <xmin>979</xmin>
      <ymin>39</ymin>
      <xmax>1022</xmax>
      <ymax>70</ymax>
    </bndbox>
  </object>
  <object>
    <name>thai</name>
    <pose>Unspecified</pose>
    <truncated>0</truncated>
    <difficult>0</difficult>
    <bndbox>
      <xmin>700</xmin>
      <ymin>741</ymin>
      <xmax>1067</xmax>
      <ymax>794</ymax>
    </bndbox>
  </object>
  <object>
    <name>thai</name>
    <pose>Unspecified</pose>
    <truncated>0</truncated>
    <difficult>0</difficult>
    <bndbox>
      <xmin>154</xmin>
      <ymin>847</ymin>
      <xmax>1066</xmax>
      <ymax>1059</ymax>
    </bndbox>
  </object>
  <object>
    <name>thai</name>
    <pose>Unspecified</pose>
    <truncated>0</truncated>
    <difficult>0</difficult>
    <bndbox>
      <xmin>153</xmin>
      <ymin>1053</ymin>
      <xmax>1064</xmax>
      <ymax>1258</ymax>
    </bndbox>
  </object>
  <object>
    <name>thai</name>
    <pose>Unspecified</pose>
    <truncated>0</truncated>
    <difficult>0</difficult>
    <bndbox>
      <xmin>153</xmin>
      <ymin>1254</ymin>
      <xmax>1066</xmax>
      <ymax>1402</ymax>
    </bndbox>
  </object>
  <object>
    <name>thai</name>
    <pose>Unspecified</pose>
    <truncated>0</truncated>
    <difficult>0</difficult>
    <bndbox>
      <xmin>154</xmin>
      <ymin>1411</ymin>
      <xmax>1065</xmax>
      <ymax>1556</ymax>
    </bndbox>
  </object>
</annotation>
