<annotation>
  <folder>input</folder>
  <filename>ineWWJBk2-18.jpg</filename>
  <path>/Users/squidpurin/Documents/Labeling/OpenLabeling-master/main/input/ineWWJBk2-18.jpg</path>
  <source>
    <database>Unknown</database>
  </source>
  <size>
    <width>606</width>
    <height>905</height>
    <depth>3</depth>
  </size>
  <segmented>0</segmented>
  <object>
    <name>inuktitut</name>
    <pose>Unspecified</pose>
    <truncated>0</truncated>
    <difficult>0</difficult>
    <bndbox>
      <xmin>65</xmin>
      <ymin>77</ymin>
      <xmax>518</xmax>
      <ymax>237</ymax>
    </bndbox>
  </object>
</annotation>
