<annotation>
  <folder>input</folder>
  <filename>X00234_Latin53.jpg</filename>
  <path>/Users/squidpurin/Documents/GitHub/scrimg_new/keras-yolo3-q/Labeling/input/X00234_Latin53.jpg</path>
  <source>
    <database>Unknown</database>
  </source>
  <size>
    <width>352</width>
    <height>352</height>
    <depth>3</depth>
  </size>
  <segmented>0</segmented>
  <object>
    <name>latin</name>
    <pose>Unspecified</pose>
    <truncated>0</truncated>
    <difficult>0</difficult>
    <bndbox>
      <xmin>9</xmin>
      <ymin>107</ymin>
      <xmax>166</xmax>
      <ymax>124</ymax>
    </bndbox>
  </object>
  <object>
    <name>latin</name>
    <pose>Unspecified</pose>
    <truncated>0</truncated>
    <difficult>0</difficult>
    <bndbox>
      <xmin>8</xmin>
      <ymin>125</ymin>
      <xmax>138</xmax>
      <ymax>141</ymax>
    </bndbox>
  </object>
  <object>
    <name>latin</name>
    <pose>Unspecified</pose>
    <truncated>0</truncated>
    <difficult>0</difficult>
    <bndbox>
      <xmin>9</xmin>
      <ymin>150</ymin>
      <xmax>161</xmax>
      <ymax>162</ymax>
    </bndbox>
  </object>
  <object>
    <name>latin</name>
    <pose>Unspecified</pose>
    <truncated>0</truncated>
    <difficult>0</difficult>
    <bndbox>
      <xmin>10</xmin>
      <ymin>164</ymin>
      <xmax>156</xmax>
      <ymax>176</ymax>
    </bndbox>
  </object>
  <object>
    <name>latin</name>
    <pose>Unspecified</pose>
    <truncated>0</truncated>
    <difficult>0</difficult>
    <bndbox>
      <xmin>10</xmin>
      <ymin>180</ymin>
      <xmax>151</xmax>
      <ymax>191</ymax>
    </bndbox>
  </object>
  <object>
    <name>latin</name>
    <pose>Unspecified</pose>
    <truncated>0</truncated>
    <difficult>0</difficult>
    <bndbox>
      <xmin>9</xmin>
      <ymin>193</ymin>
      <xmax>97</xmax>
      <ymax>207</ymax>
    </bndbox>
  </object>
</annotation>
